mail_handler/__init__.py
mail_handler/render_mail.py
mail_handler/send_mail.py
pycontw_mail_handler-0.7.0.dist-info/entry_points.txt
pycontw_mail_handler-0.7.0.dist-info/LICENSE
pycontw_mail_handler-0.7.0.dist-info/WHEEL
pycontw_mail_handler-0.7.0.dist-info/METADATA
pycontw_mail_handler-0.7.0.dist-info/RECORD
